myPackage/__init__.py
myPackage/Linear/DoublyCLL.py
myPackage/Linear/DoublyLL.py
myPackage/Linear/LLQueue.py
myPackage/Linear/LLStack.py
myPackage/Linear/SinglyCLL.py
myPackage/Linear/SinglyLL.py
myPackage/Linear/__init__.py
myPackage/Nodes/DoublyNode.py
myPackage/Nodes/SinglyNode.py
myPackage/Nodes/TNode.py
myPackage/Nodes/__init__.py
myPackage/Trees/AVL.py
myPackage/Trees/BST.py
myPackage/Trees/__init__.py
myPackage/test/AVL_test.py
myPackage/test/BST_test.py
myPackage/test/DoublyCLL_test.py
myPackage/test/DoublyLL_test.py
myPackage/test/LLQueue_test.py
myPackage/test/LLStack_test.py
myPackage/test/SinglyCLL_test.py
myPackage/test/SinglyLL_test.py
myPackage/test/__init__.py
redpjpj-1.0.dist-info/METADATA
redpjpj-1.0.dist-info/WHEEL
redpjpj-1.0.dist-info/top_level.txt
redpjpj-1.0.dist-info/RECORD
