Metadata-Version: 2.1
Name: redpjpj
Version: 1.0
Summary: ENSF 338 Final Project
Author: Liam and Theodore
